{"SAFECRIME_W26": {"MC_options": ["Very safe", "Somewhat safe", "Not too safe", "Not at all safe", "Refused"], "question_text": "How safe, if at all, would you say your local community is from crime? Would you say it is", "Asian": {"Female": {"Not at all safe": 2.0, "Not too safe": 6.0, "Somewhat safe": 28.0, "Very safe": 7.0}, "Male": {"Not at all safe": 2.0, "Not too safe": 9.0, "Somewhat safe": 29.0, "Very safe": 25.0}}, "Black": {"Female": {"Not at all safe": 11.0, "Not too safe": 38.0, "Refused": 1.0, "Somewhat safe": 111.0, "Very safe": 18.0}, "Male": {"Not at all safe": 15.0, "Not too safe": 27.0, "Refused": 2.0, "Somewhat safe": 93.0, "Very safe": 24.0}}, "Hispanic": {"Female": {"Not at all safe": 3.0, "Not too safe": 15.0, "Refused": 1.0, "Somewhat safe": 40.0, "Very safe": 9.0}, "Male": {"Not at all safe": 4.0, "Not too safe": 18.0, "Somewhat safe": 49.0, "Very safe": 13.0}}, "Mixed Race": {"Female": {"Not at all safe": 5.0, "Not too safe": 11.0, "Refused": 1.0, "Somewhat safe": 37.0, "Very safe": 8.0}, "Male": {"Not at all safe": 1.0, "Not too safe": 6.0, "Somewhat safe": 31.0, "Very safe": 12.0}}, "Other": {"Female": {"Not at all safe": 2.0, "Not too safe": 2.0, "Somewhat safe": 19.0, "Very safe": 3.0}, "Male": {"Not at all safe": 1.0, "Not too safe": 1.0, "Somewhat safe": 14.0, "Very safe": 2.0}}, "Refused": {"Female": {"Not at all safe": 1.0, "Not too safe": 3.0, "Somewhat safe": 9.0, "Very safe": 4.0}, "Male": {"Not too safe": 5.0, "Somewhat safe": 19.0, "Very safe": 8.0}}, "White": {"Female": {"Not at all safe": 38.0, "Not too safe": 214.0, "Refused": 3.0, "Somewhat safe": 999.0, "Very safe": 461.0}, "Male": {"Not at all safe": 24.0, "Not too safe": 139.0, "Refused": 2.0, "Somewhat safe": 908.0, "Very safe": 575.0}}, "marginals": {"Asian": {"Not at all safe": 4.0, "Not too safe": 15.0, "Somewhat safe": 57.0, "Very safe": 32.0}, "Black": {"Not at all safe": 26.0, "Not too safe": 65.0, "Refused": 3.0, "Somewhat safe": 204.0, "Very safe": 42.0}, "Hispanic": {"Not at all safe": 7.0, "Not too safe": 33.0, "Refused": 1.0, "Somewhat safe": 89.0, "Very safe": 22.0}, "Mixed Race": {"Not at all safe": 6.0, "Not too safe": 17.0, "Refused": 1.0, "Somewhat safe": 68.0, "Very safe": 20.0}, "Other": {"Not at all safe": 3.0, "Not too safe": 3.0, "Somewhat safe": 33.0, "Very safe": 5.0}, "Refused": {"Not at all safe": 1.0, "Not too safe": 8.0, "Somewhat safe": 28.0, "Very safe": 12.0}, "White": {"Not at all safe": 62.0, "Not too safe": 353.0, "Refused": 5.0, "Somewhat safe": 1907.0, "Very safe": 1036.0}, "Female": {"Not at all safe": 62.0, "Not too safe": 289.0, "Somewhat safe": 1243.0, "Very safe": 510.0, "Refused": 6.0}, "Male": {"Not at all safe": 47.0, "Not too safe": 205.0, "Somewhat safe": 1143.0, "Very safe": 659.0, "Refused": 4.0}}}, "WORLDDANGER_W26": {"MC_options": ["We live in a safer world", "We live in a more dangerous world", "The world we live in is neither safer nor more dangerous", "Refused"], "question_text": "Compared to 50 years ago, do you think", "Asian": {"Female": {"The world we live in is neither safer nor more dangerous": 8.0, "We live in a more dangerous world": 25.0, "We live in a safer world": 10.0}, "Male": {"The world we live in is neither safer nor more dangerous": 16.0, "We live in a more dangerous world": 28.0, "We live in a safer world": 21.0}}, "Black": {"Female": {"Refused": 1.0, "The world we live in is neither safer nor more dangerous": 42.0, "We live in a more dangerous world": 127.0, "We live in a safer world": 9.0}, "Male": {"The world we live in is neither safer nor more dangerous": 34.0, "We live in a more dangerous world": 110.0, "We live in a safer world": 17.0}}, "Hispanic": {"Female": {"The world we live in is neither safer nor more dangerous": 17.0, "We live in a more dangerous world": 48.0, "We live in a safer world": 3.0}, "Male": {"Refused": 1.0, "The world we live in is neither safer nor more dangerous": 22.0, "We live in a more dangerous world": 50.0, "We live in a safer world": 11.0}}, "Mixed Race": {"Female": {"Refused": 1.0, "The world we live in is neither safer nor more dangerous": 11.0, "We live in a more dangerous world": 45.0, "We live in a safer world": 5.0}, "Male": {"The world we live in is neither safer nor more dangerous": 7.0, "We live in a more dangerous world": 39.0, "We live in a safer world": 4.0}}, "Other": {"Female": {"Refused": 1.0, "The world we live in is neither safer nor more dangerous": 2.0, "We live in a more dangerous world": 20.0, "We live in a safer world": 3.0}, "Male": {"The world we live in is neither safer nor more dangerous": 3.0, "We live in a more dangerous world": 15.0}}, "Refused": {"Female": {"The world we live in is neither safer nor more dangerous": 4.0, "We live in a more dangerous world": 12.0, "We live in a safer world": 1.0}, "Male": {"The world we live in is neither safer nor more dangerous": 9.0, "We live in a more dangerous world": 20.0, "We live in a safer world": 3.0}}, "White": {"Female": {"Refused": 2.0, "The world we live in is neither safer nor more dangerous": 310.0, "We live in a more dangerous world": 1302.0, "We live in a safer world": 101.0}, "Male": {"Refused": 5.0, "The world we live in is neither safer nor more dangerous": 341.0, "We live in a more dangerous world": 1087.0, "We live in a safer world": 215.0}}, "marginals": {"Asian": {"The world we live in is neither safer nor more dangerous": 24.0, "We live in a more dangerous world": 53.0, "We live in a safer world": 31.0}, "Black": {"Refused": 1.0, "The world we live in is neither safer nor more dangerous": 76.0, "We live in a more dangerous world": 237.0, "We live in a safer world": 26.0}, "Hispanic": {"The world we live in is neither safer nor more dangerous": 39.0, "We live in a more dangerous world": 98.0, "We live in a safer world": 14.0, "Refused": 1.0}, "Mixed Race": {"Refused": 1.0, "The world we live in is neither safer nor more dangerous": 18.0, "We live in a more dangerous world": 84.0, "We live in a safer world": 9.0}, "Other": {"Refused": 1.0, "The world we live in is neither safer nor more dangerous": 5.0, "We live in a more dangerous world": 35.0, "We live in a safer world": 3.0}, "Refused": {"The world we live in is neither safer nor more dangerous": 13.0, "We live in a more dangerous world": 32.0, "We live in a safer world": 4.0}, "White": {"Refused": 7.0, "The world we live in is neither safer nor more dangerous": 651.0, "We live in a more dangerous world": 2389.0, "We live in a safer world": 316.0}, "Female": {"The world we live in is neither safer nor more dangerous": 394.0, "We live in a more dangerous world": 1579.0, "We live in a safer world": 132.0, "Refused": 5.0}, "Male": {"The world we live in is neither safer nor more dangerous": 432.0, "We live in a more dangerous world": 1349.0, "We live in a safer world": 271.0, "Refused": 6.0}}}, "WORRYG_W26": {"MC_options": ["Worry a lot", "Worry a little", "Do not worry at all", "Refused"], "question_text": "How much, if at all, do you worry about the following happening to you? Having a personal health crisis", "Asian": {"Female": {"Do not worry at all": 3.0, "Worry a little": 24.0, "Worry a lot": 16.0}, "Male": {"Do not worry at all": 11.0, "Worry a little": 34.0, "Worry a lot": 20.0}}, "Black": {"Female": {"Do not worry at all": 43.0, "Refused": 1.0, "Worry a little": 79.0, "Worry a lot": 56.0}, "Male": {"Do not worry at all": 36.0, "Worry a little": 87.0, "Worry a lot": 38.0}}, "Hispanic": {"Female": {"Do not worry at all": 10.0, "Worry a little": 27.0, "Worry a lot": 31.0}, "Male": {"Do not worry at all": 14.0, "Worry a little": 47.0, "Worry a lot": 23.0}}, "Mixed Race": {"Female": {"Do not worry at all": 12.0, "Worry a little": 36.0, "Worry a lot": 14.0}, "Male": {"Do not worry at all": 12.0, "Worry a little": 27.0, "Worry a lot": 11.0}}, "Other": {"Female": {"Do not worry at all": 3.0, "Refused": 1.0, "Worry a little": 15.0, "Worry a lot": 7.0}, "Male": {"Do not worry at all": 2.0, "Worry a little": 11.0, "Worry a lot": 5.0}}, "Refused": {"Female": {"Do not worry at all": 5.0, "Worry a little": 7.0, "Worry a lot": 5.0}, "Male": {"Do not worry at all": 6.0, "Worry a little": 20.0, "Worry a lot": 6.0}}, "White": {"Female": {"Do not worry at all": 261.0, "Refused": 5.0, "Worry a little": 1033.0, "Worry a lot": 416.0}, "Male": {"Do not worry at all": 324.0, "Refused": 4.0, "Worry a little": 1022.0, "Worry a lot": 298.0}}, "marginals": {"Asian": {"Do not worry at all": 14.0, "Worry a little": 58.0, "Worry a lot": 36.0}, "Black": {"Do not worry at all": 79.0, "Refused": 1.0, "Worry a little": 166.0, "Worry a lot": 94.0}, "Hispanic": {"Do not worry at all": 24.0, "Worry a little": 74.0, "Worry a lot": 54.0}, "Mixed Race": {"Do not worry at all": 24.0, "Worry a little": 63.0, "Worry a lot": 25.0}, "Other": {"Do not worry at all": 5.0, "Refused": 1.0, "Worry a little": 26.0, "Worry a lot": 12.0}, "Refused": {"Do not worry at all": 11.0, "Worry a little": 27.0, "Worry a lot": 11.0}, "White": {"Do not worry at all": 585.0, "Refused": 9.0, "Worry a little": 2055.0, "Worry a lot": 714.0}, "Female": {"Do not worry at all": 337.0, "Worry a little": 1221.0, "Worry a lot": 545.0, "Refused": 7.0}, "Male": {"Do not worry at all": 405.0, "Worry a little": 1248.0, "Worry a lot": 401.0, "Refused": 4.0}}}, "GUN_W26": {"MC_options": ["Yes", "I own a gun", "\"No", "I don't own any guns\"", "Refused"], "question_text": "Do you personally own any guns (not including air guns, such as paintball, BB or pellet guns)?", "Asian": {"Female": {"No, I don't own any guns": 39.0, "Yes, I own a gun": 4.0}, "Male": {"No, I don't own any guns": 59.0, "Refused": 1.0, "Yes, I own a gun": 5.0}}, "Black": {"Female": {"No, I don't own any guns": 150.0, "Refused": 1.0, "Yes, I own a gun": 28.0}, "Male": {"No, I don't own any guns": 100.0, "Refused": 1.0, "Yes, I own a gun": 60.0}}, "Hispanic": {"Female": {"No, I don't own any guns": 60.0, "Refused": 2.0, "Yes, I own a gun": 6.0}, "Male": {"No, I don't own any guns": 64.0, "Refused": 2.0, "Yes, I own a gun": 18.0}}, "Mixed Race": {"Female": {"No, I don't own any guns": 47.0, "Refused": 1.0, "Yes, I own a gun": 14.0}, "Male": {"No, I don't own any guns": 26.0, "Refused": 1.0, "Yes, I own a gun": 23.0}}, "Other": {"Female": {"No, I don't own any guns": 14.0, "Refused": 1.0, "Yes, I own a gun": 11.0}, "Male": {"No, I don't own any guns": 8.0, "Refused": 1.0, "Yes, I own a gun": 9.0}}, "Refused": {"Female": {"No, I don't own any guns": 11.0, "Refused": 1.0, "Yes, I own a gun": 5.0}, "Male": {"No, I don't own any guns": 14.0, "Refused": 2.0, "Yes, I own a gun": 16.0}}, "White": {"Female": {"No, I don't own any guns": 1324.0, "Refused": 22.0, "Yes, I own a gun": 369.0}, "Male": {"No, I don't own any guns": 867.0, "Refused": 20.0, "Yes, I own a gun": 761.0}}, "marginals": {"Asian": {"No, I don't own any guns": 98.0, "Yes, I own a gun": 9.0, "Refused": 1.0}, "Black": {"No, I don't own any guns": 250.0, "Refused": 2.0, "Yes, I own a gun": 88.0}, "Hispanic": {"No, I don't own any guns": 124.0, "Refused": 4.0, "Yes, I own a gun": 24.0}, "Mixed Race": {"No, I don't own any guns": 73.0, "Refused": 2.0, "Yes, I own a gun": 37.0}, "Other": {"No, I don't own any guns": 22.0, "Refused": 2.0, "Yes, I own a gun": 20.0}, "Refused": {"No, I don't own any guns": 25.0, "Refused": 3.0, "Yes, I own a gun": 21.0}, "White": {"No, I don't own any guns": 2191.0, "Refused": 42.0, "Yes, I own a gun": 1130.0}, "Female": {"No, I don't own any guns": 1645.0, "Yes, I own a gun": 437.0, "Refused": 28.0}, "Male": {"No, I don't own any guns": 1138.0, "Refused": 28.0, "Yes, I own a gun": 892.0}}}, "GUN1_W26": {"MC_options": ["Yes", "someone else in my household owns a gun", "No", "no one else in my household owns a gun", "Refused"], "question_text": "Does anyone else in your household own any guns (not including air guns, such as paintball, BB or pellet guns)?", "Asian": {"Female": {"No, no one else in my household owns a gun": 31.0, "Yes, someone else in my household owns a gun": 12.0}, "Male": {"No, no one else in my household owns a gun": 59.0, "Refused": 2.0, "Yes, someone else in my household owns a gun": 4.0}}, "Black": {"Female": {"No, no one else in my household owns a gun": 146.0, "Refused": 2.0, "Yes, someone else in my household owns a gun": 31.0}, "Male": {"No, no one else in my household owns a gun": 128.0, "Refused": 2.0, "Yes, someone else in my household owns a gun": 31.0}}, "Hispanic": {"Female": {"No, no one else in my household owns a gun": 52.0, "Refused": 2.0, "Yes, someone else in my household owns a gun": 14.0}, "Male": {"No, no one else in my household owns a gun": 72.0, "Refused": 2.0, "Yes, someone else in my household owns a gun": 10.0}}, "Mixed Race": {"Female": {"No, no one else in my household owns a gun": 40.0, "Refused": 1.0, "Yes, someone else in my household owns a gun": 21.0}, "Male": {"No, no one else in my household owns a gun": 33.0, "Refused": 1.0, "Yes, someone else in my household owns a gun": 16.0}}, "Other": {"Female": {"No, no one else in my household owns a gun": 15.0, "Refused": 1.0, "Yes, someone else in my household owns a gun": 10.0}, "Male": {"No, no one else in my household owns a gun": 11.0, "Refused": 1.0, "Yes, someone else in my household owns a gun": 6.0}}, "Refused": {"Female": {"No, no one else in my household owns a gun": 9.0, "Refused": 1.0, "Yes, someone else in my household owns a gun": 7.0}, "Male": {"No, no one else in my household owns a gun": 24.0, "Refused": 3.0, "Yes, someone else in my household owns a gun": 5.0}}, "White": {"Female": {"No, no one else in my household owns a gun": 1089.0, "Refused": 21.0, "Yes, someone else in my household owns a gun": 605.0}, "Male": {"No, no one else in my household owns a gun": 1246.0, "Refused": 23.0, "Yes, someone else in my household owns a gun": 379.0}}, "marginals": {"Asian": {"No, no one else in my household owns a gun": 90.0, "Yes, someone else in my household owns a gun": 16.0, "Refused": 2.0}, "Black": {"No, no one else in my household owns a gun": 274.0, "Refused": 4.0, "Yes, someone else in my household owns a gun": 62.0}, "Hispanic": {"No, no one else in my household owns a gun": 124.0, "Refused": 4.0, "Yes, someone else in my household owns a gun": 24.0}, "Mixed Race": {"No, no one else in my household owns a gun": 73.0, "Refused": 2.0, "Yes, someone else in my household owns a gun": 37.0}, "Other": {"No, no one else in my household owns a gun": 26.0, "Refused": 2.0, "Yes, someone else in my household owns a gun": 16.0}, "Refused": {"No, no one else in my household owns a gun": 33.0, "Refused": 4.0, "Yes, someone else in my household owns a gun": 12.0}, "White": {"No, no one else in my household owns a gun": 2335.0, "Refused": 44.0, "Yes, someone else in my household owns a gun": 984.0}, "Female": {"No, no one else in my household owns a gun": 1382.0, "Yes, someone else in my household owns a gun": 700.0, "Refused": 28.0}, "Male": {"No, no one else in my household owns a gun": 1573.0, "Refused": 34.0, "Yes, someone else in my household owns a gun": 451.0}}}, "EVERSHOT_W26": {"MC_options": ["Yes", "I have fired a gun", "No", "I have never fired a gun", "Refused"], "question_text": "Regardless of whether or not you own a gun, have you ever fired a gun?", "Asian": {"Female": {"No, I have never fired a gun": 17.0, "Yes, I have fired a gun": 26.0}, "Male": {"No, I have never fired a gun": 32.0, "Refused": 1.0, "Yes, I have fired a gun": 32.0}}, "Black": {"Female": {"No, I have never fired a gun": 97.0, "Yes, I have fired a gun": 82.0}, "Male": {"No, I have never fired a gun": 34.0, "Yes, I have fired a gun": 127.0}}, "Hispanic": {"Female": {"No, I have never fired a gun": 38.0, "Refused": 1.0, "Yes, I have fired a gun": 29.0}, "Male": {"No, I have never fired a gun": 24.0, "Yes, I have fired a gun": 60.0}}, "Mixed Race": {"Female": {"No, I have never fired a gun": 16.0, "Yes, I have fired a gun": 46.0}, "Male": {"No, I have never fired a gun": 4.0, "Refused": 1.0, "Yes, I have fired a gun": 45.0}}, "Other": {"Female": {"No, I have never fired a gun": 5.0, "Refused": 1.0, "Yes, I have fired a gun": 20.0}, "Male": {"No, I have never fired a gun": 4.0, "Yes, I have fired a gun": 14.0}}, "Refused": {"Female": {"No, I have never fired a gun": 2.0, "Yes, I have fired a gun": 15.0}, "Male": {"No, I have never fired a gun": 2.0, "Yes, I have fired a gun": 30.0}}, "White": {"Female": {"No, I have never fired a gun": 547.0, "Refused": 4.0, "Yes, I have fired a gun": 1164.0}, "Male": {"No, I have never fired a gun": 138.0, "Refused": 4.0, "Yes, I have fired a gun": 1506.0}}, "marginals": {"Asian": {"No, I have never fired a gun": 49.0, "Yes, I have fired a gun": 58.0, "Refused": 1.0}, "Black": {"No, I have never fired a gun": 131.0, "Yes, I have fired a gun": 209.0}, "Hispanic": {"No, I have never fired a gun": 62.0, "Refused": 1.0, "Yes, I have fired a gun": 89.0}, "Mixed Race": {"No, I have never fired a gun": 20.0, "Yes, I have fired a gun": 91.0, "Refused": 1.0}, "Other": {"No, I have never fired a gun": 9.0, "Refused": 1.0, "Yes, I have fired a gun": 34.0}, "Refused": {"No, I have never fired a gun": 4.0, "Yes, I have fired a gun": 45.0}, "White": {"No, I have never fired a gun": 685.0, "Refused": 8.0, "Yes, I have fired a gun": 2670.0}, "Female": {"No, I have never fired a gun": 722.0, "Yes, I have fired a gun": 1382.0, "Refused": 6.0}, "Male": {"No, I have never fired a gun": 238.0, "Refused": 6.0, "Yes, I have fired a gun": 1814.0}}}, "GUNSOCIETY_W26": {"MC_options": ["Positive way", "Negative way", "Refused"], "question_text": "Do you feel that society in general tends to look at most gun owners in a positive way or a negative way?", "Asian": {"Female": {"Negative way": 37.0, "Positive way": 6.0}, "Male": {"Negative way": 52.0, "Positive way": 13.0}}, "Black": {"Female": {"Negative way": 111.0, "Positive way": 65.0, "Refused": 3.0}, "Male": {"Negative way": 96.0, "Positive way": 63.0, "Refused": 2.0}}, "Hispanic": {"Female": {"Negative way": 50.0, "Positive way": 17.0, "Refused": 1.0}, "Male": {"Negative way": 50.0, "Positive way": 33.0, "Refused": 1.0}}, "Mixed Race": {"Female": {"Negative way": 39.0, "Positive way": 23.0}, "Male": {"Negative way": 26.0, "Positive way": 24.0}}, "Other": {"Female": {"Negative way": 16.0, "Positive way": 9.0, "Refused": 1.0}, "Male": {"Negative way": 13.0, "Positive way": 5.0}}, "Refused": {"Female": {"Negative way": 9.0, "Positive way": 7.0, "Refused": 1.0}, "Male": {"Negative way": 16.0, "Positive way": 15.0, "Refused": 1.0}}, "White": {"Female": {"Negative way": 957.0, "Positive way": 721.0, "Refused": 37.0}, "Male": {"Negative way": 876.0, "Positive way": 747.0, "Refused": 25.0}}, "marginals": {"Asian": {"Negative way": 89.0, "Positive way": 19.0}, "Black": {"Negative way": 207.0, "Positive way": 128.0, "Refused": 5.0}, "Hispanic": {"Negative way": 100.0, "Positive way": 50.0, "Refused": 2.0}, "Mixed Race": {"Negative way": 65.0, "Positive way": 47.0}, "Other": {"Negative way": 29.0, "Positive way": 14.0, "Refused": 1.0}, "Refused": {"Negative way": 25.0, "Positive way": 22.0, "Refused": 2.0}, "White": {"Negative way": 1833.0, "Positive way": 1468.0, "Refused": 62.0}, "Female": {"Negative way": 1219.0, "Positive way": 848.0, "Refused": 43.0}, "Male": {"Negative way": 1129.0, "Positive way": 900.0, "Refused": 29.0}}}, "GUNCOMMUNITY_W26": {"MC_options": ["Positive way", "Negative way", "Refused"], "question_text": "Do you feel that people in your local community tend to look at most gun owners in a positive way or a negative way?", "Asian": {"Female": {"Negative way": 25.0, "Positive way": 16.0, "Refused": 2.0}, "Male": {"Negative way": 42.0, "Positive way": 22.0, "Refused": 1.0}}, "Black": {"Female": {"Negative way": 89.0, "Positive way": 85.0, "Refused": 5.0}, "Male": {"Negative way": 76.0, "Positive way": 82.0, "Refused": 3.0}}, "Hispanic": {"Female": {"Negative way": 46.0, "Positive way": 19.0, "Refused": 3.0}, "Male": {"Negative way": 41.0, "Positive way": 41.0, "Refused": 2.0}}, "Mixed Race": {"Female": {"Negative way": 26.0, "Positive way": 35.0, "Refused": 1.0}, "Male": {"Negative way": 15.0, "Positive way": 35.0}}, "Other": {"Female": {"Negative way": 8.0, "Positive way": 17.0, "Refused": 1.0}, "Male": {"Negative way": 10.0, "Positive way": 8.0}}, "Refused": {"Female": {"Negative way": 1.0, "Positive way": 15.0, "Refused": 1.0}, "Male": {"Negative way": 13.0, "Positive way": 18.0, "Refused": 1.0}}, "White": {"Female": {"Negative way": 593.0, "Positive way": 1083.0, "Refused": 39.0}, "Male": {"Negative way": 490.0, "Positive way": 1132.0, "Refused": 26.0}}, "marginals": {"Asian": {"Negative way": 67.0, "Positive way": 38.0, "Refused": 3.0}, "Black": {"Negative way": 165.0, "Positive way": 167.0, "Refused": 8.0}, "Hispanic": {"Negative way": 87.0, "Positive way": 60.0, "Refused": 5.0}, "Mixed Race": {"Negative way": 41.0, "Positive way": 70.0, "Refused": 1.0}, "Other": {"Negative way": 18.0, "Positive way": 25.0, "Refused": 1.0}, "Refused": {"Negative way": 14.0, "Positive way": 33.0, "Refused": 2.0}, "White": {"Negative way": 1083.0, "Positive way": 2215.0, "Refused": 65.0}, "Female": {"Negative way": 788.0, "Positive way": 1270.0, "Refused": 52.0}, "Male": {"Negative way": 687.0, "Positive way": 1338.0, "Refused": 33.0}}}, "GUNCOURSES_W26": {"MC_options": ["Yes", "No", "Refused"], "question_text": "Have you ever taken any gun safety courses such as weapons training, hunter safety or firearm safety?", "Asian": {"Female": {"No": 33.0, "Yes": 10.0}, "Male": {"No": 49.0, "Refused": 1.0, "Yes": 15.0}}, "Black": {"Female": {"No": 146.0, "Refused": 1.0, "Yes": 32.0}, "Male": {"No": 101.0, "Refused": 1.0, "Yes": 59.0}}, "Hispanic": {"Female": {"No": 55.0, "Refused": 1.0, "Yes": 12.0}, "Male": {"No": 50.0, "Yes": 34.0}}, "Mixed Race": {"Female": {"No": 37.0, "Refused": 1.0, "Yes": 24.0}, "Male": {"No": 19.0, "Yes": 31.0}}, "Other": {"Female": {"No": 18.0, "Refused": 1.0, "Yes": 7.0}, "Male": {"No": 6.0, "Yes": 12.0}}, "Refused": {"Female": {"No": 12.0, "Yes": 5.0}, "Male": {"No": 12.0, "Yes": 20.0}}, "White": {"Female": {"No": 1308.0, "Refused": 9.0, "Yes": 398.0}, "Male": {"No": 715.0, "Refused": 7.0, "Yes": 926.0}}, "marginals": {"Asian": {"No": 82.0, "Yes": 25.0, "Refused": 1.0}, "Black": {"No": 247.0, "Refused": 2.0, "Yes": 91.0}, "Hispanic": {"No": 105.0, "Refused": 1.0, "Yes": 46.0}, "Mixed Race": {"No": 56.0, "Refused": 1.0, "Yes": 55.0}, "Other": {"No": 24.0, "Refused": 1.0, "Yes": 19.0}, "Refused": {"No": 24.0, "Yes": 25.0}, "White": {"No": 2023.0, "Refused": 16.0, "Yes": 1324.0}, "Female": {"No": 1609.0, "Yes": 488.0, "Refused": 13.0}, "Male": {"No": 952.0, "Refused": 9.0, "Yes": 1097.0}}}, "GUNCONTRIBA_W26": {"MC_options": ["A great deal", "A fair amount", "Not too much", "Not at all", "Refused"], "question_text": "How much, if at all, do you think the ease with which people can legally obtain guns contributes to gun violence in the country today?", "Asian": {"Female": {"A fair amount": 10.0, "A great deal": 20.0, "Not at all": 4.0, "Not too much": 9.0}, "Male": {"A fair amount": 23.0, "A great deal": 25.0, "Not at all": 6.0, "Not too much": 10.0, "Refused": 1.0}}, "Black": {"Female": {"A fair amount": 62.0, "A great deal": 69.0, "Not at all": 12.0, "Not too much": 32.0, "Refused": 4.0}, "Male": {"A fair amount": 54.0, "A great deal": 75.0, "Not at all": 13.0, "Not too much": 18.0, "Refused": 1.0}}, "Hispanic": {"Female": {"A fair amount": 18.0, "A great deal": 35.0, "Not at all": 3.0, "Not too much": 10.0, "Refused": 2.0}, "Male": {"A fair amount": 22.0, "A great deal": 31.0, "Not at all": 8.0, "Not too much": 23.0}}, "Mixed Race": {"Female": {"A fair amount": 23.0, "A great deal": 16.0, "Not at all": 9.0, "Not too much": 14.0}, "Male": {"A fair amount": 7.0, "A great deal": 12.0, "Not at all": 17.0, "Not too much": 14.0}}, "Other": {"Female": {"A fair amount": 8.0, "A great deal": 9.0, "Not at all": 3.0, "Not too much": 5.0, "Refused": 1.0}, "Male": {"A fair amount": 6.0, "A great deal": 4.0, "Not at all": 4.0, "Not too much": 4.0}}, "Refused": {"Female": {"A fair amount": 5.0, "A great deal": 6.0, "Not at all": 2.0, "Not too much": 4.0}, "Male": {"A fair amount": 6.0, "A great deal": 7.0, "Not at all": 9.0, "Not too much": 10.0}}, "White": {"Female": {"A fair amount": 504.0, "A great deal": 603.0, "Not at all": 194.0, "Not too much": 410.0, "Refused": 4.0}, "Male": {"A fair amount": 419.0, "A great deal": 398.0, "Not at all": 294.0, "Not too much": 531.0, "Refused": 6.0}}, "marginals": {"Asian": {"A fair amount": 33.0, "A great deal": 45.0, "Not at all": 10.0, "Not too much": 19.0, "Refused": 1.0}, "Black": {"A fair amount": 116.0, "A great deal": 144.0, "Not at all": 25.0, "Not too much": 50.0, "Refused": 5.0}, "Hispanic": {"A fair amount": 40.0, "A great deal": 66.0, "Not at all": 11.0, "Not too much": 33.0, "Refused": 2.0}, "Mixed Race": {"A fair amount": 30.0, "A great deal": 28.0, "Not at all": 26.0, "Not too much": 28.0}, "Other": {"A fair amount": 14.0, "A great deal": 13.0, "Not at all": 7.0, "Not too much": 9.0, "Refused": 1.0}, "Refused": {"A fair amount": 11.0, "A great deal": 13.0, "Not at all": 11.0, "Not too much": 14.0}, "White": {"A fair amount": 923.0, "A great deal": 1001.0, "Not at all": 488.0, "Not too much": 941.0, "Refused": 10.0}, "Female": {"A fair amount": 630.0, "A great deal": 758.0, "Not at all": 227.0, "Not too much": 484.0, "Refused": 11.0}, "Male": {"A fair amount": 537.0, "A great deal": 552.0, "Not at all": 351.0, "Not too much": 610.0, "Refused": 8.0}}}, "GUNCONTRIBB_W26": {"MC_options": ["A great deal", "A fair amount", "Not too much", "Not at all", "Refused"], "question_text": "How much, if at all, do you think the ease with which people can illegally obtain guns contributes to gun violence in the country today?", "Asian": {"Female": {"A fair amount": 8.0, "A great deal": 25.0, "Not at all": 3.0, "Not too much": 7.0}, "Male": {"A fair amount": 15.0, "A great deal": 37.0, "Not at all": 2.0, "Not too much": 11.0}}, "Black": {"Female": {"A fair amount": 36.0, "A great deal": 116.0, "Not at all": 9.0, "Not too much": 17.0, "Refused": 1.0}, "Male": {"A fair amount": 32.0, "A great deal": 115.0, "Not at all": 3.0, "Not too much": 10.0, "Refused": 1.0}}, "Hispanic": {"Female": {"A fair amount": 17.0, "A great deal": 43.0, "Not at all": 3.0, "Not too much": 4.0, "Refused": 1.0}, "Male": {"A fair amount": 27.0, "A great deal": 48.0, "Not at all": 3.0, "Not too much": 6.0}}, "Mixed Race": {"Female": {"A fair amount": 14.0, "A great deal": 42.0, "Not at all": 2.0, "Not too much": 4.0}, "Male": {"A fair amount": 16.0, "A great deal": 25.0, "Not at all": 2.0, "Not too much": 7.0}}, "Other": {"Female": {"A fair amount": 5.0, "A great deal": 20.0, "Refused": 1.0}, "Male": {"A fair amount": 4.0, "A great deal": 7.0, "Not at all": 2.0, "Not too much": 5.0}}, "Refused": {"Female": {"A fair amount": 5.0, "A great deal": 10.0, "Not at all": 1.0, "Not too much": 1.0}, "Male": {"A fair amount": 14.0, "A great deal": 11.0, "Not at all": 3.0, "Not too much": 4.0}}, "White": {"Female": {"A fair amount": 493.0, "A great deal": 1077.0, "Not at all": 42.0, "Not too much": 98.0, "Refused": 5.0}, "Male": {"A fair amount": 571.0, "A great deal": 845.0, "Not at all": 64.0, "Not too much": 164.0, "Refused": 4.0}}, "marginals": {"Asian": {"A fair amount": 23.0, "A great deal": 62.0, "Not at all": 5.0, "Not too much": 18.0}, "Black": {"A fair amount": 68.0, "A great deal": 231.0, "Not at all": 12.0, "Not too much": 27.0, "Refused": 2.0}, "Hispanic": {"A fair amount": 44.0, "A great deal": 91.0, "Not at all": 6.0, "Not too much": 10.0, "Refused": 1.0}, "Mixed Race": {"A fair amount": 30.0, "A great deal": 67.0, "Not at all": 4.0, "Not too much": 11.0}, "Other": {"A fair amount": 9.0, "A great deal": 27.0, "Refused": 1.0, "Not at all": 2.0, "Not too much": 5.0}, "Refused": {"A fair amount": 19.0, "A great deal": 21.0, "Not at all": 4.0, "Not too much": 5.0}, "White": {"A fair amount": 1064.0, "A great deal": 1922.0, "Not at all": 106.0, "Not too much": 262.0, "Refused": 9.0}, "Female": {"A fair amount": 578.0, "A great deal": 1333.0, "Not at all": 60.0, "Not too much": 131.0, "Refused": 8.0}, "Male": {"A fair amount": 679.0, "A great deal": 1088.0, "Not at all": 79.0, "Not too much": 207.0, "Refused": 5.0}}}, "GROWUPVIOL_W26": {"MC_options": ["A very big problem", "A moderately big problem", "A small problem", "Not a problem at all", "Refused"], "question_text": "How much of a problem was gun violence in the community where you spent the majority of time when you were growing up?", "Asian": {"Female": {"A moderately big problem": 5.0, "A small problem": 13.0, "A very big problem": 1.0, "Not a problem at all": 24.0}, "Male": {"A moderately big problem": 9.0, "A small problem": 17.0, "A very big problem": 2.0, "Not a problem at all": 37.0}}, "Black": {"Female": {"A moderately big problem": 37.0, "A small problem": 60.0, "A very big problem": 15.0, "Not a problem at all": 66.0, "Refused": 1.0}, "Male": {"A moderately big problem": 31.0, "A small problem": 54.0, "A very big problem": 23.0, "Not a problem at all": 52.0, "Refused": 1.0}}, "Hispanic": {"Female": {"A moderately big problem": 13.0, "A small problem": 18.0, "A very big problem": 2.0, "Not a problem at all": 34.0, "Refused": 1.0}, "Male": {"A moderately big problem": 15.0, "A small problem": 25.0, "A very big problem": 12.0, "Not a problem at all": 32.0}}, "Mixed Race": {"Female": {"A moderately big problem": 8.0, "A small problem": 18.0, "A very big problem": 1.0, "Not a problem at all": 35.0}, "Male": {"A moderately big problem": 6.0, "A small problem": 16.0, "A very big problem": 2.0, "Not a problem at all": 26.0}}, "Other": {"Female": {"A moderately big problem": 1.0, "A small problem": 6.0, "A very big problem": 2.0, "Not a problem at all": 16.0, "Refused": 1.0}, "Male": {"A moderately big problem": 6.0, "A small problem": 2.0, "Not a problem at all": 10.0}}, "Refused": {"Female": {"A moderately big problem": 2.0, "A small problem": 4.0, "A very big problem": 1.0, "Not a problem at all": 10.0}, "Male": {"A moderately big problem": 2.0, "A small problem": 6.0, "A very big problem": 2.0, "Not a problem at all": 22.0}}, "White": {"Female": {"A moderately big problem": 71.0, "A small problem": 376.0, "A very big problem": 25.0, "Not a problem at all": 1236.0, "Refused": 7.0}, "Male": {"A moderately big problem": 69.0, "A small problem": 404.0, "A very big problem": 24.0, "Not a problem at all": 1148.0, "Refused": 3.0}}, "marginals": {"Asian": {"A moderately big problem": 14.0, "A small problem": 30.0, "A very big problem": 3.0, "Not a problem at all": 61.0}, "Black": {"A moderately big problem": 68.0, "A small problem": 114.0, "A very big problem": 38.0, "Not a problem at all": 118.0, "Refused": 2.0}, "Hispanic": {"A moderately big problem": 28.0, "A small problem": 43.0, "A very big problem": 14.0, "Not a problem at all": 66.0, "Refused": 1.0}, "Mixed Race": {"A moderately big problem": 14.0, "A small problem": 34.0, "A very big problem": 3.0, "Not a problem at all": 61.0}, "Other": {"A moderately big problem": 7.0, "A small problem": 8.0, "A very big problem": 2.0, "Not a problem at all": 26.0, "Refused": 1.0}, "Refused": {"A moderately big problem": 4.0, "A small problem": 10.0, "A very big problem": 3.0, "Not a problem at all": 32.0}, "White": {"A moderately big problem": 140.0, "A small problem": 780.0, "A very big problem": 49.0, "Not a problem at all": 2384.0, "Refused": 10.0}, "Female": {"A moderately big problem": 137.0, "A small problem": 495.0, "A very big problem": 47.0, "Not a problem at all": 1421.0, "Refused": 10.0}, "Male": {"A moderately big problem": 138.0, "A small problem": 524.0, "A very big problem": 65.0, "Not a problem at all": 1327.0, "Refused": 4.0}}}, "GROWUPGUN1_W26": {"MC_options": ["Yes", "there were guns in my household", "No", "there were no guns in my household", "I am not sure if there were guns in my household", "Refused"], "question_text": "Thinking about when you were growing up, as far as you know, were there ever any guns in your household or not?", "Asian": {"Female": {"I am not sure if there were guns in my household": 3.0, "No, there were no guns in my household": 31.0, "Yes, there were guns in my household": 9.0}, "Male": {"I am not sure if there were guns in my household": 5.0, "No, there were no guns in my household": 50.0, "Refused": 1.0, "Yes, there were guns in my household": 9.0}}, "Black": {"Female": {"I am not sure if there were guns in my household": 24.0, "No, there were no guns in my household": 83.0, "Refused": 1.0, "Yes, there were guns in my household": 71.0}, "Male": {"I am not sure if there were guns in my household": 17.0, "No, there were no guns in my household": 70.0, "Refused": 1.0, "Yes, there were guns in my household": 73.0}}, "Hispanic": {"Female": {"I am not sure if there were guns in my household": 6.0, "No, there were no guns in my household": 41.0, "Refused": 1.0, "Yes, there were guns in my household": 20.0}, "Male": {"I am not sure if there were guns in my household": 9.0, "No, there were no guns in my household": 46.0, "Refused": 1.0, "Yes, there were guns in my household": 28.0}}, "Mixed Race": {"Female": {"I am not sure if there were guns in my household": 9.0, "No, there were no guns in my household": 18.0, "Yes, there were guns in my household": 35.0}, "Male": {"I am not sure if there were guns in my household": 3.0, "No, there were no guns in my household": 20.0, "Yes, there were guns in my household": 27.0}}, "Other": {"Female": {"I am not sure if there were guns in my household": 3.0, "No, there were no guns in my household": 9.0, "Refused": 1.0, "Yes, there were guns in my household": 13.0}, "Male": {"I am not sure if there were guns in my household": 2.0, "No, there were no guns in my household": 6.0, "Yes, there were guns in my household": 10.0}}, "Refused": {"Female": {"I am not sure if there were guns in my household": 5.0, "No, there were no guns in my household": 4.0, "Yes, there were guns in my household": 8.0}, "Male": {"I am not sure if there were guns in my household": 1.0, "No, there were no guns in my household": 13.0, "Yes, there were guns in my household": 18.0}}, "White": {"Female": {"I am not sure if there were guns in my household": 126.0, "No, there were no guns in my household": 735.0, "Refused": 7.0, "Yes, there were guns in my household": 847.0}, "Male": {"I am not sure if there were guns in my household": 57.0, "No, there were no guns in my household": 606.0, "Refused": 4.0, "Yes, there were guns in my household": 981.0}}, "marginals": {"Asian": {"I am not sure if there were guns in my household": 8.0, "No, there were no guns in my household": 81.0, "Yes, there were guns in my household": 18.0, "Refused": 1.0}, "Black": {"I am not sure if there were guns in my household": 41.0, "No, there were no guns in my household": 153.0, "Refused": 2.0, "Yes, there were guns in my household": 144.0}, "Hispanic": {"I am not sure if there were guns in my household": 15.0, "No, there were no guns in my household": 87.0, "Refused": 2.0, "Yes, there were guns in my household": 48.0}, "Mixed Race": {"I am not sure if there were guns in my household": 12.0, "No, there were no guns in my household": 38.0, "Yes, there were guns in my household": 62.0}, "Other": {"I am not sure if there were guns in my household": 5.0, "No, there were no guns in my household": 15.0, "Refused": 1.0, "Yes, there were guns in my household": 23.0}, "Refused": {"I am not sure if there were guns in my household": 6.0, "No, there were no guns in my household": 17.0, "Yes, there were guns in my household": 26.0}, "White": {"I am not sure if there were guns in my household": 183.0, "No, there were no guns in my household": 1341.0, "Refused": 11.0, "Yes, there were guns in my household": 1828.0}, "Female": {"I am not sure if there were guns in my household": 176.0, "No, there were no guns in my household": 921.0, "Yes, there were guns in my household": 1003.0, "Refused": 10.0}, "Male": {"I am not sure if there were guns in my household": 94.0, "No, there were no guns in my household": 811.0, "Refused": 7.0, "Yes, there were guns in my household": 1146.0}}}, "GROWUPGUN7_W26": {"MC_options": ["Often", "Sometimes", "Hardly ever", "Never", "Refused"], "question_text": "How often, if ever, did you use air guns, such as paintball, BB or pellet guns when you were growing up?", "Asian": {"Female": {"Hardly ever": 4.0, "Never": 33.0, "Often": 3.0, "Sometimes": 3.0}, "Male": {"Hardly ever": 24.0, "Never": 20.0, "Often": 7.0, "Sometimes": 14.0}}, "Black": {"Female": {"Hardly ever": 36.0, "Never": 110.0, "Often": 7.0, "Refused": 2.0, "Sometimes": 24.0}, "Male": {"Hardly ever": 42.0, "Never": 43.0, "Often": 33.0, "Sometimes": 43.0}}, "Hispanic": {"Female": {"Hardly ever": 16.0, "Never": 43.0, "Often": 4.0, "Refused": 1.0, "Sometimes": 4.0}, "Male": {"Hardly ever": 25.0, "Never": 19.0, "Often": 12.0, "Sometimes": 28.0}}, "Mixed Race": {"Female": {"Hardly ever": 13.0, "Never": 27.0, "Often": 7.0, "Sometimes": 15.0}, "Male": {"Hardly ever": 9.0, "Never": 10.0, "Often": 16.0, "Sometimes": 15.0}}, "Other": {"Female": {"Hardly ever": 4.0, "Never": 11.0, "Often": 2.0, "Refused": 1.0, "Sometimes": 8.0}, "Male": {"Hardly ever": 1.0, "Never": 4.0, "Often": 8.0, "Sometimes": 5.0}}, "Refused": {"Female": {"Hardly ever": 6.0, "Never": 9.0, "Sometimes": 2.0}, "Male": {"Hardly ever": 6.0, "Never": 7.0, "Often": 7.0, "Sometimes": 12.0}}, "White": {"Female": {"Hardly ever": 328.0, "Never": 1071.0, "Often": 85.0, "Refused": 8.0, "Sometimes": 223.0}, "Male": {"Hardly ever": 406.0, "Never": 251.0, "Often": 469.0, "Refused": 2.0, "Sometimes": 520.0}}, "marginals": {"Asian": {"Hardly ever": 28.0, "Never": 53.0, "Often": 10.0, "Sometimes": 17.0}, "Black": {"Hardly ever": 78.0, "Never": 153.0, "Often": 40.0, "Refused": 2.0, "Sometimes": 67.0}, "Hispanic": {"Hardly ever": 41.0, "Never": 62.0, "Often": 16.0, "Refused": 1.0, "Sometimes": 32.0}, "Mixed Race": {"Hardly ever": 22.0, "Never": 37.0, "Often": 23.0, "Sometimes": 30.0}, "Other": {"Hardly ever": 5.0, "Never": 15.0, "Often": 10.0, "Refused": 1.0, "Sometimes": 13.0}, "Refused": {"Hardly ever": 12.0, "Never": 16.0, "Sometimes": 14.0, "Often": 7.0}, "White": {"Hardly ever": 734.0, "Never": 1322.0, "Often": 554.0, "Refused": 10.0, "Sometimes": 743.0}, "Female": {"Hardly ever": 407.0, "Never": 1304.0, "Often": 108.0, "Sometimes": 279.0, "Refused": 12.0}, "Male": {"Hardly ever": 513.0, "Never": 354.0, "Often": 552.0, "Sometimes": 637.0, "Refused": 2.0}}}, "DEFENDGUN_W26": {"MC_options": ["Yes", "No", "Refused"], "question_text": "Not including in military combat or as part of your job, have you ever used a gun to defend yourself, your family or possessions, either by firing it or threatening to fire it?", "Asian": {"Female": {"No": 42.0, "Yes": 1.0}, "Male": {"No": 61.0, "Refused": 4.0}}, "Black": {"Female": {"No": 166.0, "Refused": 1.0, "Yes": 12.0}, "Male": {"No": 129.0, "Refused": 1.0, "Yes": 31.0}}, "Hispanic": {"Female": {"No": 65.0, "Refused": 1.0, "Yes": 2.0}, "Male": {"No": 75.0, "Yes": 9.0}}, "Mixed Race": {"Female": {"No": 55.0, "Yes": 7.0}, "Male": {"No": 42.0, "Yes": 8.0}}, "Other": {"Female": {"No": 22.0, "Refused": 1.0, "Yes": 3.0}, "Male": {"No": 16.0, "Yes": 2.0}}, "Refused": {"Female": {"No": 17.0}, "Male": {"No": 27.0, "Yes": 5.0}}, "White": {"Female": {"No": 1635.0, "Refused": 6.0, "Yes": 74.0}, "Male": {"No": 1517.0, "Refused": 7.0, "Yes": 124.0}}, "marginals": {"Asian": {"No": 103.0, "Yes": 1.0, "Refused": 4.0}, "Black": {"No": 295.0, "Refused": 2.0, "Yes": 43.0}, "Hispanic": {"No": 140.0, "Refused": 1.0, "Yes": 11.0}, "Mixed Race": {"No": 97.0, "Yes": 15.0}, "Other": {"No": 38.0, "Refused": 1.0, "Yes": 5.0}, "Refused": {"No": 44.0, "Yes": 5.0}, "White": {"No": 3152.0, "Refused": 13.0, "Yes": 198.0}, "Female": {"No": 2002.0, "Yes": 99.0, "Refused": 9.0}, "Male": {"No": 1867.0, "Refused": 12.0, "Yes": 179.0}}}, "GUNTHREAT_W26": {"MC_options": ["Yes", "No", "Refused"], "question_text": "Has anyone ever used a gun to threaten or intimidate you or someone in your family?", "Asian": {"Female": {"No": 39.0, "Yes": 4.0}, "Male": {"No": 57.0, "Refused": 2.0, "Yes": 6.0}}, "Black": {"Female": {"No": 119.0, "Yes": 60.0}, "Male": {"No": 94.0, "Yes": 67.0}}, "Hispanic": {"Female": {"No": 49.0, "Refused": 2.0, "Yes": 17.0}, "Male": {"No": 61.0, "Yes": 23.0}}, "Mixed Race": {"Female": {"No": 44.0, "Yes": 18.0}, "Male": {"No": 28.0, "Yes": 22.0}}, "Other": {"Female": {"No": 20.0, "Refused": 1.0, "Yes": 5.0}, "Male": {"No": 13.0, "Yes": 5.0}}, "Refused": {"Female": {"No": 16.0, "Yes": 1.0}, "Male": {"No": 22.0, "Yes": 10.0}}, "White": {"Female": {"No": 1396.0, "Refused": 5.0, "Yes": 314.0}, "Male": {"No": 1287.0, "Refused": 5.0, "Yes": 356.0}}, "marginals": {"Asian": {"No": 96.0, "Yes": 10.0, "Refused": 2.0}, "Black": {"No": 213.0, "Yes": 127.0}, "Hispanic": {"No": 110.0, "Refused": 2.0, "Yes": 40.0}, "Mixed Race": {"No": 72.0, "Yes": 40.0}, "Other": {"No": 33.0, "Refused": 1.0, "Yes": 10.0}, "Refused": {"No": 38.0, "Yes": 11.0}, "White": {"No": 2683.0, "Refused": 10.0, "Yes": 670.0}, "Female": {"No": 1683.0, "Yes": 419.0, "Refused": 8.0}, "Male": {"No": 1562.0, "Refused": 7.0, "Yes": 489.0}}}, "CRIMEVICTIM_W26": {"MC_options": ["Yes", "No", "Refused"], "question_text": "Have you ever been a victim of a violent crime, whether a gun was used or not?", "Asian": {"Female": {"No": 37.0, "Yes": 6.0}, "Male": {"No": 60.0, "Yes": 5.0}}, "Black": {"Female": {"No": 140.0, "Refused": 1.0, "Yes": 38.0}, "Male": {"No": 109.0, "Refused": 2.0, "Yes": 50.0}}, "Hispanic": {"Female": {"No": 51.0, "Refused": 1.0, "Yes": 16.0}, "Male": {"No": 62.0, "Yes": 22.0}}, "Mixed Race": {"Female": {"No": 34.0, "Yes": 28.0}, "Male": {"No": 25.0, "Yes": 25.0}}, "Other": {"Female": {"No": 22.0, "Refused": 1.0, "Yes": 3.0}, "Male": {"No": 13.0, "Yes": 5.0}}, "Refused": {"Female": {"No": 14.0, "Yes": 3.0}, "Male": {"No": 23.0, "Yes": 9.0}}, "White": {"Female": {"No": 1435.0, "Refused": 8.0, "Yes": 272.0}, "Male": {"No": 1374.0, "Refused": 4.0, "Yes": 270.0}}, "marginals": {"Asian": {"No": 97.0, "Yes": 11.0}, "Black": {"No": 249.0, "Refused": 3.0, "Yes": 88.0}, "Hispanic": {"No": 113.0, "Refused": 1.0, "Yes": 38.0}, "Mixed Race": {"No": 59.0, "Yes": 53.0}, "Other": {"No": 35.0, "Refused": 1.0, "Yes": 8.0}, "Refused": {"No": 37.0, "Yes": 12.0}, "White": {"No": 2809.0, "Refused": 12.0, "Yes": 542.0}, "Female": {"No": 1733.0, "Yes": 366.0, "Refused": 11.0}, "Male": {"No": 1666.0, "Yes": 386.0, "Refused": 6.0}}}, "GUNACTIVITYA_W26": {"MC_options": ["Often", "Sometimes", "Hardly ever", "Never", "Refused"], "question_text": "How often, if ever, do you visit websites about guns, hunting or other shooting sports", "Asian": {"Female": {"Hardly ever": 5.0, "Never": 35.0, "Often": 1.0, "Sometimes": 2.0}, "Male": {"Hardly ever": 17.0, "Never": 44.0, "Often": 1.0, "Refused": 1.0, "Sometimes": 2.0}}, "Black": {"Female": {"Hardly ever": 18.0, "Never": 149.0, "Often": 3.0, "Refused": 2.0, "Sometimes": 7.0}, "Male": {"Hardly ever": 35.0, "Never": 97.0, "Often": 7.0, "Refused": 2.0, "Sometimes": 20.0}}, "Hispanic": {"Female": {"Hardly ever": 6.0, "Never": 56.0, "Often": 1.0, "Refused": 2.0, "Sometimes": 3.0}, "Male": {"Hardly ever": 24.0, "Never": 48.0, "Sometimes": 12.0}}, "Mixed Race": {"Female": {"Hardly ever": 7.0, "Never": 47.0, "Often": 1.0, "Refused": 1.0, "Sometimes": 6.0}, "Male": {"Hardly ever": 13.0, "Never": 23.0, "Often": 4.0, "Sometimes": 10.0}}, "Other": {"Female": {"Hardly ever": 6.0, "Never": 15.0, "Often": 1.0, "Refused": 1.0, "Sometimes": 3.0}, "Male": {"Hardly ever": 7.0, "Never": 2.0, "Often": 1.0, "Sometimes": 8.0}}, "Refused": {"Female": {"Hardly ever": 1.0, "Never": 15.0, "Sometimes": 1.0}, "Male": {"Hardly ever": 10.0, "Never": 13.0, "Often": 2.0, "Sometimes": 7.0}}, "White": {"Female": {"Hardly ever": 188.0, "Never": 1408.0, "Often": 14.0, "Refused": 5.0, "Sometimes": 100.0}, "Male": {"Hardly ever": 370.0, "Never": 940.0, "Often": 52.0, "Refused": 3.0, "Sometimes": 283.0}}, "marginals": {"Asian": {"Hardly ever": 22.0, "Never": 79.0, "Often": 2.0, "Sometimes": 4.0, "Refused": 1.0}, "Black": {"Hardly ever": 53.0, "Never": 246.0, "Often": 10.0, "Refused": 4.0, "Sometimes": 27.0}, "Hispanic": {"Hardly ever": 30.0, "Never": 104.0, "Often": 1.0, "Refused": 2.0, "Sometimes": 15.0}, "Mixed Race": {"Hardly ever": 20.0, "Never": 70.0, "Often": 5.0, "Refused": 1.0, "Sometimes": 16.0}, "Other": {"Hardly ever": 13.0, "Never": 17.0, "Often": 2.0, "Refused": 1.0, "Sometimes": 11.0}, "Refused": {"Hardly ever": 11.0, "Never": 28.0, "Sometimes": 8.0, "Often": 2.0}, "White": {"Hardly ever": 558.0, "Never": 2348.0, "Often": 66.0, "Refused": 8.0, "Sometimes": 383.0}, "Female": {"Hardly ever": 231.0, "Never": 1725.0, "Often": 21.0, "Sometimes": 122.0, "Refused": 11.0}, "Male": {"Hardly ever": 476.0, "Never": 1167.0, "Often": 67.0, "Refused": 6.0, "Sometimes": 342.0}}}, "GUNACTIVITYB_W26": {"MC_options": ["Often", "Sometimes", "Hardly ever", "Never", "Refused"], "question_text": "How often, if ever, do you watch TV programs about guns or watch gun-oriented videos", "Asian": {"Female": {"Hardly ever": 7.0, "Never": 29.0, "Often": 4.0, "Sometimes": 3.0}, "Male": {"Hardly ever": 16.0, "Never": 32.0, "Often": 2.0, "Sometimes": 15.0}}, "Black": {"Female": {"Hardly ever": 35.0, "Never": 103.0, "Often": 12.0, "Refused": 1.0, "Sometimes": 28.0}, "Male": {"Hardly ever": 37.0, "Never": 70.0, "Often": 12.0, "Refused": 3.0, "Sometimes": 39.0}}, "Hispanic": {"Female": {"Hardly ever": 10.0, "Never": 40.0, "Often": 3.0, "Refused": 1.0, "Sometimes": 14.0}, "Male": {"Hardly ever": 21.0, "Never": 36.0, "Often": 6.0, "Sometimes": 21.0}}, "Mixed Race": {"Female": {"Hardly ever": 13.0, "Never": 32.0, "Often": 6.0, "Sometimes": 11.0}, "Male": {"Hardly ever": 16.0, "Never": 12.0, "Often": 4.0, "Refused": 1.0, "Sometimes": 17.0}}, "Other": {"Female": {"Hardly ever": 6.0, "Never": 12.0, "Often": 3.0, "Refused": 1.0, "Sometimes": 4.0}, "Male": {"Hardly ever": 9.0, "Never": 2.0, "Often": 1.0, "Sometimes": 6.0}}, "Refused": {"Female": {"Hardly ever": 4.0, "Never": 9.0, "Often": 1.0, "Sometimes": 3.0}, "Male": {"Hardly ever": 11.0, "Never": 10.0, "Often": 1.0, "Sometimes": 10.0}}, "White": {"Female": {"Hardly ever": 370.0, "Never": 1052.0, "Often": 63.0, "Refused": 8.0, "Sometimes": 222.0}, "Male": {"Hardly ever": 528.0, "Never": 673.0, "Often": 64.0, "Refused": 3.0, "Sometimes": 380.0}}, "marginals": {"Asian": {"Hardly ever": 23.0, "Never": 61.0, "Often": 6.0, "Sometimes": 18.0}, "Black": {"Hardly ever": 72.0, "Never": 173.0, "Often": 24.0, "Refused": 4.0, "Sometimes": 67.0}, "Hispanic": {"Hardly ever": 31.0, "Never": 76.0, "Often": 9.0, "Refused": 1.0, "Sometimes": 35.0}, "Mixed Race": {"Hardly ever": 29.0, "Never": 44.0, "Often": 10.0, "Sometimes": 28.0, "Refused": 1.0}, "Other": {"Hardly ever": 15.0, "Never": 14.0, "Often": 4.0, "Refused": 1.0, "Sometimes": 10.0}, "Refused": {"Hardly ever": 15.0, "Never": 19.0, "Often": 2.0, "Sometimes": 13.0}, "White": {"Hardly ever": 898.0, "Never": 1725.0, "Often": 127.0, "Refused": 11.0, "Sometimes": 602.0}, "Female": {"Hardly ever": 445.0, "Never": 1277.0, "Often": 92.0, "Sometimes": 285.0, "Refused": 11.0}, "Male": {"Hardly ever": 638.0, "Never": 835.0, "Often": 90.0, "Sometimes": 488.0, "Refused": 7.0}}}, "GUNACTIVITYC_W26": {"MC_options": ["Often", "Sometimes", "Hardly ever", "Never", "Refused"], "question_text": "How often, if ever, do you listen to gun-oriented podcasts or radio shows", "Asian": {"Female": {"Never": 39.0, "Often": 1.0, "Refused": 1.0, "Sometimes": 2.0}, "Male": {"Hardly ever": 6.0, "Never": 55.0, "Refused": 1.0, "Sometimes": 3.0}}, "Black": {"Female": {"Hardly ever": 19.0, "Never": 150.0, "Often": 2.0, "Refused": 1.0, "Sometimes": 7.0}, "Male": {"Hardly ever": 18.0, "Never": 133.0, "Often": 1.0, "Refused": 2.0, "Sometimes": 7.0}}, "Hispanic": {"Female": {"Hardly ever": 6.0, "Never": 51.0, "Often": 2.0, "Refused": 1.0, "Sometimes": 8.0}, "Male": {"Hardly ever": 19.0, "Never": 56.0, "Often": 1.0, "Sometimes": 8.0}}, "Mixed Race": {"Female": {"Hardly ever": 4.0, "Never": 54.0, "Sometimes": 4.0}, "Male": {"Hardly ever": 6.0, "Never": 36.0, "Often": 1.0, "Sometimes": 7.0}}, "Other": {"Female": {"Hardly ever": 2.0, "Never": 21.0, "Often": 2.0, "Refused": 1.0}, "Male": {"Hardly ever": 4.0, "Never": 10.0, "Often": 1.0, "Sometimes": 3.0}}, "Refused": {"Female": {"Never": 16.0, "Sometimes": 1.0}, "Male": {"Hardly ever": 10.0, "Never": 17.0, "Often": 1.0, "Sometimes": 4.0}}, "White": {"Female": {"Hardly ever": 142.0, "Never": 1496.0, "Often": 13.0, "Refused": 12.0, "Sometimes": 52.0}, "Male": {"Hardly ever": 255.0, "Never": 1283.0, "Often": 5.0, "Refused": 6.0, "Sometimes": 99.0}}, "marginals": {"Asian": {"Never": 94.0, "Often": 1.0, "Refused": 2.0, "Sometimes": 5.0, "Hardly ever": 6.0}, "Black": {"Hardly ever": 37.0, "Never": 283.0, "Often": 3.0, "Refused": 3.0, "Sometimes": 14.0}, "Hispanic": {"Hardly ever": 25.0, "Never": 107.0, "Often": 3.0, "Refused": 1.0, "Sometimes": 16.0}, "Mixed Race": {"Hardly ever": 10.0, "Never": 90.0, "Sometimes": 11.0, "Often": 1.0}, "Other": {"Hardly ever": 6.0, "Never": 31.0, "Often": 3.0, "Refused": 1.0, "Sometimes": 3.0}, "Refused": {"Never": 33.0, "Sometimes": 5.0, "Hardly ever": 10.0, "Often": 1.0}, "White": {"Hardly ever": 397.0, "Never": 2779.0, "Often": 18.0, "Refused": 18.0, "Sometimes": 151.0}, "Female": {"Never": 1827.0, "Often": 20.0, "Refused": 16.0, "Sometimes": 74.0, "Hardly ever": 173.0}, "Male": {"Hardly ever": 318.0, "Never": 1590.0, "Refused": 9.0, "Sometimes": 131.0, "Often": 10.0}}}, "GUNACTIVITYD_W26": {"MC_options": ["Often", "Sometimes", "Hardly ever", "Never", "Refused"], "question_text": "How often, if ever, do you participate in online discussion forums about guns", "Asian": {"Female": {"Hardly ever": 4.0, "Never": 39.0}, "Male": {"Hardly ever": 9.0, "Never": 51.0, "Refused": 1.0, "Sometimes": 4.0}}, "Black": {"Female": {"Hardly ever": 19.0, "Never": 152.0, "Often": 2.0, "Refused": 2.0, "Sometimes": 4.0}, "Male": {"Hardly ever": 19.0, "Never": 132.0, "Often": 2.0, "Refused": 2.0, "Sometimes": 6.0}}, "Hispanic": {"Female": {"Hardly ever": 9.0, "Never": 58.0, "Refused": 1.0}, "Male": {"Hardly ever": 13.0, "Never": 67.0, "Often": 1.0, "Sometimes": 3.0}}, "Mixed Race": {"Female": {"Hardly ever": 5.0, "Never": 53.0, "Often": 1.0, "Sometimes": 3.0}, "Male": {"Hardly ever": 11.0, "Never": 33.0, "Often": 3.0, "Sometimes": 3.0}}, "Other": {"Female": {"Hardly ever": 1.0, "Never": 20.0, "Refused": 1.0, "Sometimes": 4.0}, "Male": {"Hardly ever": 1.0, "Never": 13.0, "Sometimes": 4.0}}, "Refused": {"Female": {"Hardly ever": 1.0, "Never": 16.0}, "Male": {"Hardly ever": 8.0, "Never": 22.0, "Often": 1.0, "Sometimes": 1.0}}, "White": {"Female": {"Hardly ever": 157.0, "Never": 1495.0, "Often": 5.0, "Refused": 10.0, "Sometimes": 48.0}, "Male": {"Hardly ever": 251.0, "Never": 1319.0, "Often": 12.0, "Refused": 4.0, "Sometimes": 62.0}}, "marginals": {"Asian": {"Hardly ever": 13.0, "Never": 90.0, "Refused": 1.0, "Sometimes": 4.0}, "Black": {"Hardly ever": 38.0, "Never": 284.0, "Often": 4.0, "Refused": 4.0, "Sometimes": 10.0}, "Hispanic": {"Hardly ever": 22.0, "Never": 125.0, "Refused": 1.0, "Often": 1.0, "Sometimes": 3.0}, "Mixed Race": {"Hardly ever": 16.0, "Never": 86.0, "Often": 4.0, "Sometimes": 6.0}, "Other": {"Hardly ever": 2.0, "Never": 33.0, "Refused": 1.0, "Sometimes": 8.0}, "Refused": {"Hardly ever": 9.0, "Never": 38.0, "Often": 1.0, "Sometimes": 1.0}, "White": {"Hardly ever": 408.0, "Never": 2814.0, "Often": 17.0, "Refused": 14.0, "Sometimes": 110.0}, "Female": {"Hardly ever": 196.0, "Never": 1833.0, "Often": 8.0, "Refused": 14.0, "Sometimes": 59.0}, "Male": {"Hardly ever": 312.0, "Never": 1637.0, "Refused": 7.0, "Sometimes": 83.0, "Often": 19.0}}}, "GUNACTIVITYE_W26": {"MC_options": ["Often", "Sometimes", "Hardly ever", "Never", "Refused"], "question_text": "How often, if ever, do you attend gun shows", "Asian": {"Female": {"Hardly ever": 1.0, "Never": 40.0, "Sometimes": 2.0}, "Male": {"Hardly ever": 5.0, "Never": 56.0, "Often": 1.0, "Refused": 1.0, "Sometimes": 2.0}}, "Black": {"Female": {"Hardly ever": 11.0, "Never": 160.0, "Often": 1.0, "Refused": 2.0, "Sometimes": 5.0}, "Male": {"Hardly ever": 22.0, "Never": 125.0, "Often": 1.0, "Refused": 1.0, "Sometimes": 12.0}}, "Hispanic": {"Female": {"Hardly ever": 3.0, "Never": 60.0, "Often": 1.0, "Refused": 1.0, "Sometimes": 3.0}, "Male": {"Hardly ever": 13.0, "Never": 66.0, "Often": 1.0, "Sometimes": 4.0}}, "Mixed Race": {"Female": {"Hardly ever": 5.0, "Never": 50.0, "Sometimes": 7.0}, "Male": {"Hardly ever": 12.0, "Never": 30.0, "Often": 2.0, "Sometimes": 6.0}}, "Other": {"Female": {"Hardly ever": 4.0, "Never": 18.0, "Refused": 1.0, "Sometimes": 3.0}, "Male": {"Hardly ever": 3.0, "Never": 10.0, "Often": 1.0, "Sometimes": 4.0}}, "Refused": {"Female": {"Hardly ever": 3.0, "Never": 14.0}, "Male": {"Hardly ever": 11.0, "Never": 13.0, "Often": 2.0, "Refused": 1.0, "Sometimes": 5.0}}, "White": {"Female": {"Hardly ever": 157.0, "Never": 1448.0, "Often": 9.0, "Refused": 6.0, "Sometimes": 95.0}, "Male": {"Hardly ever": 350.0, "Never": 1099.0, "Often": 19.0, "Refused": 9.0, "Sometimes": 171.0}}, "marginals": {"Asian": {"Hardly ever": 6.0, "Never": 96.0, "Sometimes": 4.0, "Often": 1.0, "Refused": 1.0}, "Black": {"Hardly ever": 33.0, "Never": 285.0, "Often": 2.0, "Refused": 3.0, "Sometimes": 17.0}, "Hispanic": {"Hardly ever": 16.0, "Never": 126.0, "Often": 2.0, "Refused": 1.0, "Sometimes": 7.0}, "Mixed Race": {"Hardly ever": 17.0, "Never": 80.0, "Sometimes": 13.0, "Often": 2.0}, "Other": {"Hardly ever": 7.0, "Never": 28.0, "Refused": 1.0, "Sometimes": 7.0, "Often": 1.0}, "Refused": {"Hardly ever": 14.0, "Never": 27.0, "Often": 2.0, "Refused": 1.0, "Sometimes": 5.0}, "White": {"Hardly ever": 507.0, "Never": 2547.0, "Often": 28.0, "Refused": 15.0, "Sometimes": 266.0}, "Female": {"Hardly ever": 184.0, "Never": 1790.0, "Sometimes": 115.0, "Often": 11.0, "Refused": 10.0}, "Male": {"Hardly ever": 416.0, "Never": 1399.0, "Often": 27.0, "Refused": 12.0, "Sometimes": 204.0}}}}